mathw/__init__.py
mathw/formatter.py
mathw/series/__init__.py
mathw/series/add.py
mathw/series/mult.py
mathw/series/utils.py
mathw-1.2.0.dist-info/METADATA
mathw-1.2.0.dist-info/WHEEL
mathw-1.2.0.dist-info/licenses/LICENSE
mathw-1.2.0.dist-info/RECORD
