Metadata-Version: 2.3
Name: mathw
Version: 1.2.0
Summary: Children's Math Practice.
Project-URL: Homepage, https://github.com/xianqiu/math-homework
Author-email: xqiu <x.qiu@qq.com>
License-File: LICENSE
Classifier: License :: OSI Approved :: MIT License
Classifier: Operating System :: OS Independent
Classifier: Programming Language :: Python :: 3
Requires-Python: >=3.6
Requires-Dist: numpy>=1.2.34
Requires-Dist: reportlab>=3.6.12
